README.md
aisvue
setup.py
aisastack.egg-info/PKG-INFO
aisastack.egg-info/SOURCES.txt
aisastack.egg-info/dependency_links.txt
aisastack.egg-info/requires.txt
aisastack.egg-info/top_level.txt
builders/__init__.py
builders/blight.py