Metadata-Version: 2.1
Name: aisastack
Version: 1.0.1
Summary: Command Line Tools for creating skeleton project in FrontEnd (django rest)
Home-page: https://github.com/aisahana/aisastack
Author: Aisahana
Author-email: aisahana.business@gmail.com
License: UNKNOWN
Platform: UNKNOWN
Classifier: Programming Language :: Python :: 3
Classifier: License :: OSI Approved :: MIT License
Classifier: Operating System :: OS Independent
